django_csrf_protect_form/__init__.py
django_csrf_protect_form-0.1.0.dist-info/LICENSE
django_csrf_protect_form-0.1.0.dist-info/METADATA
django_csrf_protect_form-0.1.0.dist-info/WHEEL
django_csrf_protect_form-0.1.0.dist-info/top_level.txt
django_csrf_protect_form-0.1.0.dist-info/RECORD
