Metadata-Version: 2.1
Name: django-csrf-protect-form
Version: 0.1.0
Summary: Enable CSRF protection only for HTML forms
Home-page: https://github.com/dex4er/django-csrf-protect-form
Author: Piotr Roszatycki
Author-email: piotr.roszatycki@gmail.com
License: LGPL
Keywords: django html view csrf protect
Platform: OS Independent
Classifier: Development Status :: 3 - Alpha
Classifier: Environment :: Web Environment
Classifier: Intended Audience :: Developers
Classifier: License :: OSI Approved :: GNU Lesser General Public License v3 or later (LGPLv3+)
Classifier: Operating System :: OS Independent
Classifier: Programming Language :: Python
Classifier: Programming Language :: Python :: 2.7
Classifier: Programming Language :: Python :: 3.5
Classifier: Programming Language :: Python :: 3.6
Classifier: Programming Language :: Python :: 3.7
Classifier: Framework :: Django
Classifier: Framework :: Django :: 1.11
Classifier: Framework :: Django :: 2.0
Classifier: Framework :: Django :: 2.1
Classifier: Framework :: Django :: 2.2
Provides-Extra: dev
